sim/week01_axil/rtl/axil_regbank.v
// Purpose: Minimal AXI4-Lite register bank with CTRL (0x0) and DATA (0x4)
// Notes: Single-beat transactions, 32-bit data, handles AW/W in any order.
// Implements wstrb, OKAY for valid regs, SLVERR for others.

`timescale 1ns/1ps

module axil_regbank #(
  parameter ADDR_WIDTH = 4,
  parameter DATA_WIDTH = 32
)(
  input  wire                   ACLK,
  input  wire                   ARESETn,

  // Write address channel
  input  wire [ADDR_WIDTH-1:0]  saxi_awaddr,
  input  wire                   saxi_awvalid,
  output wire                   saxi_awready,

  // Write data channel
  input  wire [DATA_WIDTH-1:0]  saxi_wdata,
  input  wire [DATA_WIDTH/8-1:0] saxi_wstrb,
  input  wire                   saxi_wvalid,
  output wire                   saxi_wready,

  // Write response channel
  output reg  [1:0]             saxi_bresp,
  output reg                    saxi_bvalid,
  input  wire                   saxi_bready,

  // Read address channel
  input  wire [ADDR_WIDTH-1:0]  saxi_araddr,
  input  wire                   saxi_arvalid,
  output wire                   saxi_arready,

  // Read data channel
  output reg  [DATA_WIDTH-1:0]  saxi_rdata,
  output reg  [1:0]             saxi_rresp,
  output reg                    saxi_rvalid,
  input  wire                   saxi_rready
);

  localparam OKAY  = 2'b00;
  localparam SLVERR= 2'b10;

  // Simple regs
  reg [DATA_WIDTH-1:0] reg_ctrl;
  reg [DATA_WIDTH-1:0] reg_data;

  // Latching write address and data (independent arrival)
  reg                   aw_hs_done;
  reg [ADDR_WIDTH-1:0]  awaddr_q;
  reg                   w_hs_done;
  reg [DATA_WIDTH-1:0]  wdata_q;
  reg [DATA_WIDTH/8-1:0] wstrb_q;

  // Read address handshake
  reg                   ar_hs_done;
  reg [ADDR_WIDTH-1:0]  araddr_q;

  // Ready signals based on whether we've latched the payloads
  assign saxi_awready = (~aw_hs_done) & ARESETn;
  assign saxi_wready  = (~w_hs_done)  & ARESETn;
  assign saxi_arready = (~ar_hs_done) & (~saxi_rvalid) & ARESETn;

  // Write address handshake/latch
  always @(posedge ACLK or negedge ARESETn) begin
    if (!ARESETn) begin
      aw_hs_done <= 1'b0;
      awaddr_q   <= {ADDR_WIDTH{1'b0}};
    end else begin
      if (!aw_hs_done && saxi_awvalid && saxi_awready) begin
        aw_hs_done <= 1'b1;
        awaddr_q   <= saxi_awaddr;
      end
      // Clear after write response accepted
      if (saxi_bvalid && saxi_bready) begin
        aw_hs_done <= 1'b0;
      end
    end
  end

  // Write data handshake/latch
  always @(posedge ACLK or negedge ARESETn) begin
    if (!ARESETn) begin
      w_hs_done <= 1'b0;
      wdata_q   <= {DATA_WIDTH{1'b0}};
      wstrb_q   <= {DATA_WIDTH/8{1'b0}};
    end else begin
      if (!w_hs_done && saxi_wvalid && saxi_wready) begin
        w_hs_done <= 1'b1;
        wdata_q   <= saxi_wdata;
        wstrb_q   <= saxi_wstrb;
      end
      if (saxi_bvalid && saxi_bready) begin
        w_hs_done <= 1'b0;
      end
    end
  end

  // Perform the write when both AW and W are captured
  wire do_write = aw_hs_done && w_hs_done && ~saxi_bvalid;

  // Address decode on word offsets (assume 32-bit words)
  wire [1:0] word_sel_w = awaddr_q[3:2];
  wire [1:0] word_sel_r = araddr_q[3:2];

  integer i;
  always @(posedge ACLK or negedge ARESETn) begin
    if (!ARESETn) begin
      reg_ctrl   <= {DATA_WIDTH{1'b0}};
      reg_data   <= {DATA_WIDTH{1'b0}};
      saxi_bvalid <= 1'b0;
      saxi_bresp  <= OKAY;
    end else begin
      if (do_write) begin
        case (word_sel_w)
          2'b00: begin // CTRL @ 0x0
            for (i = 0; i < DATA_WIDTH/8; i = i + 1) begin
              if (wstrb_q[i]) reg_ctrl[i*8 +: 8] <= wdata_q[i*8 +: 8];
            end
            saxi_bresp <= OKAY;
          end
          2'b01: begin // DATA @ 0x4
            for (i = 0; i < DATA_WIDTH/8; i = i + 1) begin
              if (wstrb_q[i]) reg_data[i*8 +: 8] <= wdata_q[i*8 +: 8];
            end
            saxi_bresp <= OKAY;
          end
          default: begin
            // Invalid address
            saxi_bresp <= SLVERR;
          end
        endcase
        saxi_bvalid <= 1'b1;
      end
      if (saxi_bvalid && saxi_bready) begin
        saxi_bvalid <= 1'b0;
      end
    end
  end

  // Read address handshake/latch
  always @(posedge ACLK or negedge ARESETn) begin
    if (!ARESETn) begin
      ar_hs_done <= 1'b0;
      araddr_q   <= {ADDR_WIDTH{1'b0}};
      saxi_rvalid <= 1'b0;
      saxi_rresp  <= OKAY;
      saxi_rdata  <= {DATA_WIDTH{1'b0}};
    end else begin
      if (!ar_hs_done && saxi_arvalid && saxi_arready) begin
        ar_hs_done <= 1'b1;
        araddr_q   <= saxi_araddr;
        // Prepare data/resp immediately; present on rvalid
        case (saxi_araddr[3:2])
          2'b00: begin saxi_rdata <= reg_ctrl; saxi_rresp <= OKAY; end
          2'b01: begin saxi_rdata <= reg_data; saxi_rresp <= OKAY; end
          default: begin saxi_rdata <= {DATA_WIDTH{1'b0}}; saxi_rresp <= SLVERR; end
        endcase
        saxi_rvalid <= 1'b1;
      end
      if (saxi_rvalid && saxi_rready) begin
        saxi_rvalid <= 1'b0;
        ar_hs_done   <= 1'b0;
      end
    end
  end

endmodule

sim/week01_axil/dump.vcd
$version Generated by VerilatedVcd $end
$timescale 1ps $end
 $scope module  $end
  $var wire 1 # ACLK $end
  $var wire 1 $ ARESETn $end
  $var wire 4 % saxi_awaddr [3:0] $end
  $var wire 1 & saxi_awvalid $end
  $var wire 1 ' saxi_awready $end
  $var wire 32 ( saxi_wdata [31:0] $end
  $var wire 4 ) saxi_wstrb [3:0] $end
  $var wire 1 * saxi_wvalid $end
  $var wire 1 + saxi_wready $end
  $var wire 2 , saxi_bresp [1:0] $end
  $var wire 1 - saxi_bvalid $end
  $var wire 1 . saxi_bready $end
  $var wire 4 / saxi_araddr [3:0] $end
  $var wire 1 0 saxi_arvalid $end
  $var wire 1 1 saxi_arready $end
  $var wire 32 2 saxi_rdata [31:0] $end
  $var wire 2 3 saxi_rresp [1:0] $end
  $var wire 1 4 saxi_rvalid $end
  $var wire 1 5 saxi_rready $end
  $scope module axil_regbank $end
   $var wire 32 V ADDR_WIDTH [31:0] $end
   $var wire 32 W DATA_WIDTH [31:0] $end
   $var wire 1 6 ACLK $end
   $var wire 1 7 ARESETn $end
   $var wire 4 8 saxi_awaddr [3:0] $end
   $var wire 1 9 saxi_awvalid $end
   $var wire 1 : saxi_awready $end
   $var wire 32 ; saxi_wdata [31:0] $end
   $var wire 4 < saxi_wstrb [3:0] $end
   $var wire 1 = saxi_wvalid $end
   $var wire 1 > saxi_wready $end
   $var wire 2 ? saxi_bresp [1:0] $end
   $var wire 1 @ saxi_bvalid $end
   $var wire 1 A saxi_bready $end
   $var wire 4 B saxi_araddr [3:0] $end
   $var wire 1 C saxi_arvalid $end
   $var wire 1 D saxi_arready $end
   $var wire 32 E saxi_rdata [31:0] $end
   $var wire 2 F saxi_rresp [1:0] $end
   $var wire 1 G saxi_rvalid $end
   $var wire 1 H saxi_rready $end
   $var wire 2 X OKAY [1:0] $end
   $var wire 2 Y SLVERR [1:0] $end
   $var wire 32 I reg_ctrl [31:0] $end
   $var wire 32 J reg_data [31:0] $end
   $var wire 1 K aw_hs_done $end
   $var wire 4 L awaddr_q [3:0] $end
   $var wire 1 M w_hs_done $end
   $var wire 32 N wdata_q [31:0] $end
   $var wire 4 O wstrb_q [3:0] $end
   $var wire 1 P ar_hs_done $end
   $var wire 4 Q araddr_q [3:0] $end
   $var wire 1 R do_write $end
   $var wire 2 S word_sel_w [1:0] $end
   $var wire 2 T word_sel_r [1:0] $end
   $var wire 32 U i [31:0] $end
  $upscope $end
 $upscope $end
$enddefinitions $end


#0
1#
0$
b0000 %
0&
0'
b00000000000000000000000000000000 (
b0000 )
0*
0+
b00 ,
0-
0.
b0000 /
00
01
b00000000000000000000000000000000 2
b00 3
04
05
16
07
b0000 8
09
0:
b00000000000000000000000000000000 ;
b0000 <
0=
0>
b00 ?
0@
0A
b0000 B
0C
0D
b00000000000000000000000000000000 E
b00 F
0G
0H
b00000000000000000000000000000000 I
b00000000000000000000000000000000 J
0K
b0000 L
0M
b00000000000000000000000000000000 N
b0000 O
0P
b0000 Q
0R
b00 S
b00 T
b00000000000000000000000000000000 U
b00000000000000000000000000000100 V
b00000000000000000000000000100000 W
b00 X
b10 Y
#5000
0#
06
#10000
1#
16
#15000
0#
06
#20000
1#
16
#25000
0#
06
#30000
1#
16
#35000
0#
06
#40000
1#
1$
1'
1+
11
16
17
1:
1>
1D
#45000
0#
06
#50000
1#
16
#55000
0#
06
#60000
1#
16
#65000
0#
06
#70000
1#
1&
b00000000000000000000000000000001 (
b1111 )
1*
1.
15
16
19
b00000000000000000000000000000001 ;
b1111 <
1=
1A
1H
#75000
0#
06
#80000
1#
0&
0'
0*
0+
16
09
0:
0=
0>
1K
1M
b00000000000000000000000000000001 N
b1111 O
1R
#85000
0#
06
#90000
1#
1-
16
1@
b00000000000000000000000000000001 I
0R
b00000000000000000000000000000100 U
#95000
0#
06
#100000
1#
1'
1+
0-
16
1:
1>
0@
0K
0M
#105000
0#
06
#110000
1#
b0100 %
1&
b00000000000000000001001000110100 (
1*
16
b0100 8
19
b00000000000000000001001000110100 ;
1=
#115000
0#
06
#120000
1#
0&
0'
0*
0+
16
09
0:
0=
0>
1K
b0100 L
1M
b00000000000000000001001000110100 N
1R
b01 S
#125000
0#
06
#130000
1#
1-
16
1@
b00000000000000000001001000110100 J
0R
#135000
0#
06
#140000
1#
1'
1+
0-
16
1:
1>
0@
0K
0M
#145000
0#
06
#150000
1#
b0100 /
10
16
b0100 B
1C
#155000
0#
06
#160000
1#
00
01
b00000000000000000001001000110100 2
14
16
0C
0D
b00000000000000000001001000110100 E
1G
1P
b0100 Q
b01 T
#165000
0#
06
#170000
1#
11
04
16
1D
0G
0P
#170001
0$
0'
0+
01
b00000000000000000000000000000000 2
07
0:
0>
0D
b00000000000000000000000000000000 E
b00000000000000000000000000000000 I
b00000000000000000000000000000000 J
b0000 L
b00000000000000000000000000000000 N
b0000 O
b0000 Q
b00 S
b00 T
#175000
#175001
0#
06
#180001
1#
16
#185001
0#
06
#190001
1#
16
#195001
0#
06
#200001
1#
16
#205001
0#
06
#210001
1#
16
#215001
0#
06
#220001
1#
1$
1'
1+
11
16
17
1:
1>
1D
#225001
0#
06
#230001
1#
16
#235001
0#
06
#240001
1#
b0000 %
b00000000000000000000000000000000 (
b0000 )
0.
b0000 /
05
16
b0000 8
b00000000000000000000000000000000 ;
b0000 <
0A
b0000 B
0H
#245001
0#
06
#250001
1#
b0100 %
1&
b00010010001101000101011001111000 (
b1111 )
1*
1.
15
16
b0100 8
19
b00010010001101000101011001111000 ;
b1111 <
1=
1A
1H
#255001
0#
06
#260001
1#
0&
0'
0*
0+
16
09
0:
0=
0>
1K
b0100 L
1M
b00010010001101000101011001111000 N
b1111 O
1R
b01 S
#265001
0#
06
#270001
1#
1-
16
1@
b00010010001101000101011001111000 J
0R
#275001
0#
06
#280001
1#
1'
1+
0-
16
1:
1>
0@
0K
0M
#285001
0#
06
#290001
1#
1&
b00000000000000001010101111001101 (
b0011 )
1*
16
19
b00000000000000001010101111001101 ;
b0011 <
1=
#295001
0#
06
#300001
1#
0&
0'
0*
0+
16
09
0:
0=
0>
1K
1M
b00000000000000001010101111001101 N
b0011 O
1R
#305001
0#
06
#310001
1#
1-
16
1@
b00010010001101001010101111001101 J
0R
#315001
0#
06
#320001
1#
1'
1+
0-
16
1:
1>
0@
0K
0M
#325001
0#
06
#330001
1#
b0100 /
10
16
b0100 B
1C
#335001
0#
06
#340001
1#
00
01
b00010010001101001010101111001101 2
14
16
0C
0D
b00010010001101001010101111001101 E
1G
1P
b0100 Q
b01 T
#345001
0#
06
#350001
1#
11
04
16
1D
0G
0P
